<?xml version="1.0" encoding="UTF-8"?>
<objects serializationModel="Studio.02.01.00">
	<object class="EncodingSetting" id="{9f62211e-9df3-48bd-afc8-33ec1772dabb}">
		<property name="encodingFormat">
			<value>3</value>
		</property>
		<property name="quality">
			<value>15</value>
		</property>
		<property name="sampleRateMode">
			<value>1</value>
		</property>
		<relationship name="platform">
			<destination>{dbad32af-ebc9-4357-8332-64a65df83fc8}</destination>
		</relationship>
		<relationship name="encodable">
			<destination>{fad3f023-31f0-42b7-9797-37623c21cde7}</destination>
		</relationship>
	</object>
</objects>
